[
  {"X": -356.22, "Y": -1189.18, "Z": -251.97},
  {"X": -242.66, "Y": -824.14, "Z": -191.97},
  {"X": -1022.94, "Y": -1018.12, "Z": -191.97},
  {"X": -648.97, "Y": -503.69, "Z": -238.68},
  {"X": -605.14, "Y": -54.98, "Z": -96.97},
  {"X": -592.85, "Y": -344.97, "Z": -96.97},
  {"X": -295.95, "Y": -85.93, "Z": -192.97},
  {"X": -301.45, "Y": -365.97, "Z": -192.97},
  {"X": -415.73, "Y": -300.16, "极": -288.97},
  {"X": -701.09, "Y": -57.88, "Z": -288.97},
  {"X": -521.56, "Y": -511.48, "Z": -238.97},
  {"X": -742.06, "Y": -605.15, "Z": -238.97},
  {"X": -740.90, "Y": -692.61, "Z": -238.97},
  {"X": -735.53, "Y": -765.70, "Z": -238.97},
  {"X": -735.19, "Y": -851.23, "Z": -238.97},
  {"X": -474.04, "Y": -627.59, "Z": -238.97},
  {"X": -474.05, "Y": -724.02, "Z": -238.97},
  {"X": -470.57, "Y": -813.04, "Z": -238.97},
  {"X": -463.33, "Y": -868.84, "Z": -238.97},
  {"X": -265.13, "Y": -966.84, "Z": -140.97},
  {"X": -254.60, "Y": -1020.10, "Z": -140.97},
  {"X": -1082.35, "Y": 18.37, "Z": -88.97},
  {"X": -465.82, "Y": -1288.29, "Z": 7.03},
  {"X": -263.16, "Y": -1544.06, "Z": 7.03},
  {"X": -78.08, "Y": -1511.44, "Z": 7.03},
  {"X": -14.21, "Y": -1521.78, "Z": 7.03},
  {"X": -292.21, "Y": -96.19, "Z": 7.03},
  {"X": -58.50, "Y": -1310.26, "Z": 42.43},
  {"X": -134.40, "Y": -1087.03, "Z": 52.42},
  {"X": 227.57, "Y": -1120.92, "Z": 77.73},
  {"X": 310.05, "Y": -1129.47, "Z": 77.73},
  {"X": 1718.55, "Y": -301.08, "Z": 7.03},
  {"X": 1724.18, "Y": 38.94, "Z": 7.03},
  {"X": 2002.65, "Y": 457.68, "Z": 7.03},
  {"X": 2004.32, "Y": 409.58, "Z": 7.03},
  {"X": 1964.24, "Y": 464.06, "Z": 7.03},
  {"X": 1971.40, "Y": 411.22, "Z": 7.03},
  {"X": 1943.64, "Y": 462.75, "Z": 7.03},
  {"X": 1944.80, "Y": 405.90, "Z": 7.03},
  {"X": 1918.70, "Y": 456.24, "Z": 7.03},
  {"X": 1928.22, "Y": 396.64, "Z": 7.03},
  {"X": 1895.06, "Y": 454.13, "Z": 7.03},
  {"X": 1893.73, "Y": 397.36, "Z": 7.03},
  {"X": 1870.43, "Y": 443.66, "Z": 7.03},
  {"X": 1865.31, "Y": 399.13, "Z": 7.03},
  {"X": 1834.25, "Y": 455.07, "Z": 7.03},
  {"X": 1830.00, "Y": 404.60, "Z": 7.03},
  {"X": 2072.98, "Y": 396.74, "Z": 7.03},
  {"X": 2069.22, "Y": 463.92, "Z": 7.03},
  {"X": 2042.17, "Y": 416.33, "Z": 7.03},
  {"X": 2037.03, "Y": 459.19, "Z": 7.03},
  {"X": 2103.99, "Y": 404.75, "Z": 7.03},
  {"X": 2098.24, "Y": 465.56, "Z": 7.03},
  {"X": 866.94, "Y": 1579.36, "Z": 7.03},
  {"X": 403.69, "Y": -1101.29, "Z": 7.03},
  {"X": 1721.96, "Y": -577.54, "Z": 7.03},
  {"X": 894.24, "Y": 886.14, "Z": 12.19},
  {"X": 808.66, "Y": -1528.30, "Z": 9.41},
  {"X": 1705.19, "Y": -106.46, "Z": 7.60},
  {"X": -1242.29, "Y": -893.79, "Z": 7.55},
  {"X": 1200.98, "Y": -754.61, "Z": 35.03},
  {"X": 1052.78, "Y": -765.58, "Z": 37.03},
  {"X": -1315.27, "Y": 905.09, "Z": 7.03},
  {"X": -1304.35, "Y": 869.85, "Z": 7.03},
  {"X": -1317.91, "Y": 991.49, "Z": 7.03},
  {"X": -1314.10, "Y": 957.86, "Z": 7.03},
  {"X": -1311.48, "Y": 932.99, "Z": 7.03},
  {"X": -1306.60, "Y": 790.66, "Z": 7.03},
  {"X": -1304.03, "Y": 820.05, "Z": 7.03},
  {"X": -1312.82, "Y": 845.44, "Z": 7.03},
  {"X": -1317.98, "Y": 1078.00, "Z": 7.03},
  {"X": -1315.94, "Y": 1041.43, "Z": 7.03},
  {"X": -1320.57, "Y": 1020.64, "Z": 7.03},
  {"X": -1362.35, "Y": 842.56, "Z": 7.03},
  {"X": -1358.36, "Y": 818.70, "Z": 7.03},
  {"X": -1361.20, "Y": 788.80, "Z": 7.03},
  {"X": -1366.20, "Y": 869.78, "Z": 7.03},
  {"X": -1370.41, "Y": 909.67, "Z": 7.03},
  {"X": -1372.90, "Y": 933.25, "Z": 7.03},
  {"X": -1376.10, "Y": 959.00, "Z": 7.03},
  {"X": -1376.27, "Y": 1039.00, "Z": 7.03},
  {"X": -1377.23, "Y": 1082.25, "Z": 7.03},
  {"X": -1379.93, "Y": 988.22, "Z": 7.03},
  {"X": -1380.52, "Y": 1019.31, "Z": 7.03},
  {"X": -1187.03, "Y": -994.04, "Z": 96.03},
  {"X": 661.01, "Y": 1398.17, "Z": 27.12},
  {"X": -138.85, "Y": 907.10, "Z": 7.03},
  {"X": 893.21, "Y": 1248.14, "Z": 43.04},
  {"X": 997.09, "Y": 1248.15, "Z": 43.04},
  {"X": 1231.98, "Y": 1258.33, "Z": 43.04},
  {"X": 1718.60, "Y": -430.08, "Z": 70.89},
  {"X": 1734.47, "Y": -24.16, "Z": 69.69},
  {"X": 1761.50, "Y": -180.20, "Z": 87.87},
  {"X": 129.72, "Y": 1469.70, "Z": 135.05},
  {"X": 667.71, "Y": 1479.92, "Z": 174.03},
  {"X": -41.00, "Y": 1671.78, "Z": 174.03},
  {"X": 1457.02, "Y": 1332.12, "Z": 174.03},
  {"X": 434.08, "Y": 991.28, "Z": 176.00},
  {"X": 433.10, "Y": 1016.05, "Z": 176.00},
  {"X": 1793.85, "Y": 137.22, "Z": 81.46},
  {"X": -33.67, "Y": 1994.90, "Z": 94.03},
  {"X": -592.00, "Y": 1714.59, "Z": 125.03},
  {"X": -682.62, "Y": 1705.25, "Z": 125.03},
  {"X": -1352.96, "Y": -79.83, "Z": 126.34},
  {"X": -848.11, "Y": 1278.74, "Z": 129.03},
  {"X": -1042.42, "Y": 929.58, "Z": 152.94},
  {"X": -1035.64, "Y": 1116.97, "Z": 153.67},
  {"X": -904.46, "Y": 643.03, "Z": 119.07},
  {"X": -985.60, "Y": 559.07, "Z": 119.20},
  {"X": -950.02, "Y": 685.74, "Z": 120.16},
  {"X": -1044.72, "Y": 586.74, "Z": 120.25},
  {"X": 650.41, "Y": 1313.01, "Z": 196.33},
  {"X": 1058.11, "Y": 59.19, "Z": 215.03},
  {"X": 1047.03, "Y": -263.15, "Z": 215.05},
  {"X": 1182.26, "Y": 199.74, "Z": 215.59},
  {"X": 1240.67, "Y": 196.12, "Z": 216.80},
  {"X": -344.53, "Y": 304.42, "Z": 9.28},
  {"X": -344.84, "Y": 455.59, "Z": 7.85},
  {"X": -1345.77, "Y": 171.74, "Z": 40.96},
  {"X": -1378.87, "Y": 804.11, "Z": 39.95}
]